LICENSE.txt
MANIFEST.in
README.md
setup.json
setup.py
aiida_bands_inspect/__init__.py
aiida_bands_inspect/convert.py
aiida_bands_inspect/io.py
aiida_bands_inspect.egg-info/PKG-INFO
aiida_bands_inspect.egg-info/SOURCES.txt
aiida_bands_inspect.egg-info/dependency_links.txt
aiida_bands_inspect.egg-info/entry_points.txt
aiida_bands_inspect.egg-info/requires.txt
aiida_bands_inspect.egg-info/top_level.txt
aiida_bands_inspect/calculations/__init__.py
aiida_bands_inspect/calculations/align.py
aiida_bands_inspect/calculations/difference.py
aiida_bands_inspect/calculations/plot.py
aiida_bands_inspect/parsers/__init__.py
aiida_bands_inspect/parsers/align.py
aiida_bands_inspect/parsers/bands.py
aiida_bands_inspect/parsers/difference.py
aiida_bands_inspect/parsers/plot.py