Metadata-Version: 2.1
Name: aiida-bands-inspect
Version: 0.4.0
Summary: AiiDA Plugin for running bands_inspect
Home-page: https://aiida-bands-inspect.readthedocs.io
Author: Dominik Gresch
Author-email: greschd@gmx.ch
License: Apache 2.0
Keywords: bandstructure,aiida,workflows
Platform: UNKNOWN
Classifier: Development Status :: 4 - Beta
Classifier: Environment :: Plugins
Classifier: Intended Audience :: Science/Research
Classifier: License :: OSI Approved :: Apache Software License
Classifier: Programming Language :: Python :: 3.6
Classifier: Programming Language :: Python :: 3.7
Classifier: Programming Language :: Python :: 3.8
Classifier: Topic :: Scientific/Engineering :: Physics
Classifier: Framework :: AiiDA
Requires-Python: >=3.6
Provides-Extra: testing
Provides-Extra: dev_precommit
Provides-Extra: docs
Provides-Extra: dev
